pandoc_styles/__init__.py
pandoc_styles/cl_stylepacks.py
pandoc_styles/cl_tools.py
pandoc_styles/config_dir/config.yaml
pandoc_styles/config_dir/css/default.css
pandoc_styles/config_dir/filter/alignment.py
pandoc_styles/config_dir/filter/include.py
pandoc_styles/config_dir/filter/new_page.py
pandoc_styles/config_dir/filter/noindent.py
pandoc_styles/config_dir/postflight/delete_output.py
pandoc_styles/config_dir/preflight/append_to_file.py
pandoc_styles/config_dir/sass/default.scss
pandoc_styles/config_dir/sass/default_epub.scss
pandoc_styles/config_dir/sass/extra_styles.scss
pandoc_styles/config_dir/sass/navigation.scss
pandoc_styles/config_dir/styles.yaml
pandoc_styles/constants.py
pandoc_styles/filter.py
pandoc_styles/flight_scripts.py
pandoc_styles/format_mappings.py
pandoc_styles/main.py
pandoc_styles/pandoc_cmd_line_options.py
pandoc_styles/utils.py
pandoc_styles-0.9.18.dist-info/entry_points.txt
pandoc_styles-0.9.18.dist-info/LICENSE.md
pandoc_styles-0.9.18.dist-info/METADATA
pandoc_styles-0.9.18.dist-info/WHEEL
pandoc_styles-0.9.18.dist-info/RECORD
