Metadata-Version: 2.1
Name: pandoc_styles
Version: 0.9.18
Summary: A script to convert files with pandoc using styles.
Home-page: https://github.com/dickloraine/pandoc_styles
License: MIT
Keywords: pandoc,writing,text,conversion
Author: dickloraine
Author-email: dickloraine@gmx.net
Requires-Python: >=3.9,<4.0
Classifier: Development Status :: 4 - Beta
Classifier: Intended Audience :: End Users/Desktop
Classifier: License :: OSI Approved :: MIT License
Classifier: Natural Language :: English
Classifier: Operating System :: OS Independent
Classifier: Programming Language :: Python :: 3
Classifier: Programming Language :: Python :: 3.9
Classifier: Programming Language :: Python :: 3.10
Classifier: Programming Language :: Python :: 3.11
Classifier: Programming Language :: Python :: 3.12
Classifier: Programming Language :: Python :: 3.6
Classifier: Topic :: Text Processing
Requires-Dist: libsass (>=0.22.0,<0.23.0)
Requires-Dist: panflute (>=2.3.0,<3.0.0)
Requires-Dist: ruamel.yaml (>=0.16.0,<0.17.0)
Project-URL: Repository, https://github.com/dickloraine/pandoc_styles
